CHANGES.txt
LICENSE.txt
MANIFEST.in
README.md
README.txt
setup.cfg
setup.py
NFe/teste_consulta_cadastro.py
NFe/teste_distribuicao_dfe.py
NFe/teste_download_nfe.py
NFe/teste_status.py
NFe/certificadoras/certificadoras.crt
NFe/certificadoras/v1.crt
NFe/certificadoras/v1_v2_v3.crt
NFe/certificadoras/v2.crt
NFe/certificadoras/v3.crt
NFe/cnpjs/11222333000101/certificado_digital/certificado.pem
NFe/cnpjs/11222333000101/certificado_digital/chave.pem
NFe/cnpjs/11222333000101/certificado_digital/extratir.py
NFe/cnpjs/11222333000101/homologacao/cancelamento/vazio
NFe/cnpjs/11222333000101/homologacao/carta_correcao/vazio
NFe/cnpjs/11222333000101/homologacao/danfe/vazio
NFe/cnpjs/11222333000101/homologacao/inutilizacao/vazio
NFe/cnpjs/11222333000101/homologacao/nfe/vazio
NFe/cnpjs/11222333000101/homologacao/nfe/rejeitadas/vazio
NFe/cnpjs/11222333000101/homologacao/recibo/vazio
NFe/cnpjs/11222333000101/producao/cancelamento/vazio
NFe/cnpjs/11222333000101/producao/carta_correcao/vazio
NFe/cnpjs/11222333000101/producao/danfe/vazio
NFe/cnpjs/11222333000101/producao/inutilizacao/vazio
NFe/cnpjs/11222333000101/producao/nfe/vazio
NFe/cnpjs/11222333000101/producao/nfe/rejeitadas/vazio
NFe/cnpjs/11222333000101/producao/recibo/vazio
NFe/wsdl/baixar.py
NFe/wsdl/AM/homologacao/1.00/RecepcaoEvento.wsdl
NFe/wsdl/AM/homologacao/3.10/NfeAutorizacao.wsdl
NFe/wsdl/AM/homologacao/3.10/NfeConsultaCadastro.wsdl
NFe/wsdl/AM/homologacao/3.10/NfeConsultaProtocolo.wsdl
NFe/wsdl/AM/homologacao/3.10/NfeInutilizacao.wsdl
NFe/wsdl/AM/homologacao/3.10/NfeRetAutorizacao.wsdl
NFe/wsdl/AM/homologacao/3.10/NfeStatusServico.wsdl
NFe/wsdl/AM/homologacao/4.00/NfeAutorizacao.wsdl
NFe/wsdl/AM/homologacao/4.00/NfeConsultaProtocolo.wsdl
NFe/wsdl/AM/homologacao/4.00/NfeInutilizacao.wsdl
NFe/wsdl/AM/homologacao/4.00/NfeRetAutorizacao.wsdl
NFe/wsdl/AM/homologacao/4.00/NfeStatusServico.wsdl
NFe/wsdl/AM/homologacao/4.00/RecepcaoEvento.wsdl
NFe/wsdl/AM/producao/1.00/RecepcaoEvento.wsdl
pole.egg-info/PKG-INFO
pole.egg-info/SOURCES.txt
pole.egg-info/dependency_links.txt
pole.egg-info/top_level.txt
